py_vsys/__init__.py
py_vsys/account.py
py_vsys/api.py
py_vsys/chain.py
py_vsys/data_entry.py
py_vsys/dbput.py
py_vsys/log.py
py_vsys/model.py
py_vsys/tx_req.py
py_vsys/words.py
py_vsys/contract/__init__.py
py_vsys/contract/atomic_swap_ctrt.py
py_vsys/contract/atomic_swap_helper.py
py_vsys/contract/lock_ctrt.py
py_vsys/contract/nft_ctrt.py
py_vsys/contract/pay_chan_ctrt.py
py_vsys/contract/sys_ctrt.py
py_vsys/contract/tok_ctrt.py
py_vsys/contract/tok_ctrt_factory.py
py_vsys/contract/v_escrow_ctrt.py
py_vsys/contract/v_option_ctrt.py
py_vsys/contract/v_stable_swap_ctrt.py
py_vsys/contract/v_swap_ctrt.py
py_vsys/utils/__init__.py
py_vsys/utils/crypto/__init__.py
py_vsys/utils/crypto/curve_25519.py
py_vsys/utils/crypto/hashes/__init__.py
test/__init__.py
test/func_test/__init__.py
test/func_test/conftest.py
test/func_test/test_acnt.py
test/func_test/test_api.py
test/func_test/test_ctrt/__init__.py
test/func_test/test_ctrt/test_atomic_swap_ctrt.py
test/func_test/test_ctrt/test_atomic_swap_helper.py
test/func_test/test_ctrt/test_lock_ctrt.py
test/func_test/test_ctrt/test_nft_ctrt.py
test/func_test/test_ctrt/test_pay_chan_ctrt.py
test/func_test/test_ctrt/test_sys_ctrt.py
test/func_test/test_ctrt/test_tok_ctrt.py
test/func_test/test_ctrt/test_v_escrow_ctrt.py
test/func_test/test_ctrt/test_v_option_ctrt.py
test/func_test/test_ctrt/test_v_stable_swap_ctrt.py
test/func_test/test_ctrt/test_v_swap_ctrt.py
py_vsys-0.2.1.dist-info/LICENSE
py_vsys-0.2.1.dist-info/METADATA
py_vsys-0.2.1.dist-info/WHEEL
py_vsys-0.2.1.dist-info/top_level.txt
py_vsys-0.2.1.dist-info/RECORD
