Metadata-Version: 2.1
Name: py-vsys
Version: 0.2.1
Summary: The official Python SDK for VSYS APIs
Home-page: https://github.com/virtualeconomy/py-vsys
Author: V SYSTEMS
Author-email: developers@v.systems
License: MIT
Keywords: SDK,api wrapper,blockchain,vsystems,smart contract,supernode,defi
Platform: UNKNOWN
Requires-Python: >=3.7
License-File: LICENSE
Requires-Dist: aiohttp (~=3.8.1)
Requires-Dist: python-axolotl-curve25519 (~=0.4.1.post2)
Requires-Dist: base58 (~=2.1.1)
Requires-Dist: loguru (~=0.5.3)
